[
  {
    "geohash": "9q8yu",
    "value": 0.5
  },
  {
    "geohash": "9q8yv",
    "value": 0.7668453218020029
  },
  {
    "geohash": "9q8yyp",
    "value": 0.8789404786833306
  },
  {
    "geohash": "9q8yyr",
    "value": 0.6386885538060653
  },
  {
    "geohash": "9q8yyx",
    "value": 0.9033200189886444
  },
  {
    "geohash": "9q8yyz",
    "value": 0.06462186103843648
  },
  {
    "geohash": "9q8yyn",
    "value": 0.13147494820703043
  },
  {
    "geohash": "9q8yyq",
    "value": 0.485792012096662
  },
  {
    "geohash": "9q8yyw",
    "value": 0.8944640095184043
  },
  {
    "geohash": "9q8yyy",
    "value": 0.9747861262425849
  },
  {
    "geohash": "9q8yyj",
    "value": 0.9169517985098902
  },
  {
    "geohash": "9q8yym",
    "value": 0.3321914034085779
  },
  {
    "geohash": "9q8yyt",
    "value": 0.5315109056267949
  },
  {
    "geohash": "9q8yyv",
    "value": 0.8980775695307507
  },
  {
    "geohash": "9q8yyh",
    "value": 0.7416592613155965
  },
  {
    "geohash": "9q8yyk",
    "value": 0.15883669511997212
  },
  {
    "geohash": "9q8yys",
    "value": 0.3133185678262409
  },
  {
    "geohash": "9q8yyu",
    "value": 0.8394901086606922
  },
  {
    "geohash": "9q8yy5",
    "value": 0.9302727470750508
  },
  {
    "geohash": "9q8yy7",
    "value": 0.55700280605943
  },
  {
    "geohash": "9q8yye",
    "value": 0.7967112383603723
  },
  {
    "geohash": "9q8yyg",
    "value": 0.6745763118047848
  },
  {
    "geohash": "9q8yy4",
    "value": 0.9593751656198874
  },
  {
    "geohash": "9q8yy6",
    "value": 0.12328018089803028
  },
  {
    "geohash": "9q8yyd",
    "value": 0.053522949367657335
  },
  {
    "geohash": "9q8yyf",
    "value": 0.23286365006618337
  },
  {
    "geohash": "9q8yy1",
    "value": 0.03843256296231934
  },
  {
    "geohash": "9q8yy3",
    "value": 0.8163550258069916
  },
  {
    "geohash": "9q8yy9",
    "value": 0.19261115293506093
  },
  {
    "geohash": "9q8yyc",
    "value": 0.7700095163897878
  },
  {
    "geohash": "9q8yy0",
    "value": 0.40148601989296795
  },
  {
    "geohash": "9q8yy2",
    "value": 0.4161269084131226
  },
  {
    "geohash": "9q8yy8",
    "value": 0.8272773154258688
  },
  {
    "geohash": "9q8yybb",
    "value": 0.8359061779246098
  },
  {
    "geohash": "9q8yybc",
    "value": 0.964360648997242
  },
  {
    "geohash": "9q8yybf",
    "value": 0.7554079809620927
  },
  {
    "geohash": "9q8yybg",
    "value": 0.04698699676222029
  },
  {
    "geohash": "9q8yybu",
    "value": 0.23368407527885848
  },
  {
    "geohash": "9q8yybv",
    "value": 0.17992005985040382
  },
  {
    "geohash": "9q8yyby",
    "value": 0.7579461051751792
  },
  {
    "geohash": "9q8yybz",
    "value": 0.3977700938192409
  },
  {
    "geohash": "9q8yyb8",
    "value": 0.4504435164119569
  },
  {
    "geohash": "9q8yyb9",
    "value": 0.05589100997205565
  },
  {
    "geohash": "9q8yybd",
    "value": 0.5522535367105845
  },
  {
    "geohash": "9q8yybe",
    "value": 0.5101127011567667
  },
  {
    "geohash": "9q8yybs",
    "value": 0.1679983784630208
  },
  {
    "geohash": "9q8yybt",
    "value": 0.7564907607604898
  },
  {
    "geohash": "9q8yybw",
    "value": 0.5805462367715055
  },
  {
    "geohash": "9q8yybx",
    "value": 0.7219703236579673
  },
  {
    "geohash": "9q8yyb2",
    "value": 0.6369936699860816
  },
  {
    "geohash": "9q8yyb3",
    "value": 0.978013076579851
  },
  {
    "geohash": "9q8yyb6",
    "value": 0.5464088813420106
  },
  {
    "geohash": "9q8yyb7",
    "value": 0.6874331323889045
  },
  {
    "geohash": "9q8yybk",
    "value": 0.2917421312977304
  },
  {
    "geohash": "9q8yybm",
    "value": 0.579906761799561
  },
  {
    "geohash": "9q8yybq",
    "value": 0.09135192174456574
  },
  {
    "geohash": "9q8yybr",
    "value": 0.2513344693953804
  },
  {
    "geohash": "9q8yyb0",
    "value": 0.5952427664402559
  },
  {
    "geohash": "9q8yyb1",
    "value": 0.4537150085562932
  },
  {
    "geohash": "9q8yyb4",
    "value": 0.8895522451548104
  },
  {
    "geohash": "9q8yyb5",
    "value": 0.20197741134088143
  },
  {
    "geohash": "9q8yybh",
    "value": 0.21864380020017515
  },
  {
    "geohash": "9q8yybj",
    "value": 0.41579287185679714
  },
  {
    "geohash": "9q8yybn",
    "value": 0.03442615876307731
  },
  {
    "geohash": "9q8yybp",
    "value": 0.2603286566578018
  }
]